{
  "required": true,
  "package": "paulevs.betternether.mixin.common",
  "compatibilityLevel": "JAVA_8",
  "mixins": [
	"ChunkPopulateMixin",
	"MushroomMixin",
	"MapMixin",
	"MapStateMixin",
	"BoneMealMixin",
	"LightStorageMixin",
	"NetherWartMixin",
	"PlayerEntityMixin",
	"DefaultAttributeRegistryMixin",
	"DeltaFeatureMixin",
	"SpawnRestrictionMixin",
	"BrewingRecipeRegistryMixin",
	"ServerWorldMixin",
	"MultiNoiseBiomeSourceMixin",
	"BiomeMixin",
	"RecipeManagerMixin",
	"CraftingScreenHandlerMixin",
	"PickaxeItemMixin",
	"ServerPlayNetworkHandlerMixin",
	"SheepEntityMixin"
  ],
  "injectors": {
    "defaultRequire": 1
  }
}
